conn_jack/__init__.py
conn_jack/qt.py
conn_jack-1.3.0.dist-info/LICENSE
conn_jack-1.3.0.dist-info/WHEEL
conn_jack-1.3.0.dist-info/METADATA
conn_jack-1.3.0.dist-info/RECORD
