Metadata-Version: 2.1
Name: conn_jack
Version: 1.3.0
Summary: Classes for managing jack client connections.
Author-email: Leon Dionne <ldionne@dridesign.sh.cn>
Classifier: License :: OSI Approved :: GNU General Public License v3 or later (GPLv3+)
Requires-Dist: pyjacklib
Requires-Dist: log_soso
Requires-Dist: PyQt5 ; extra == "qt"
Requires-Dist: soso_qt_extras >= 1.2.0 ; extra == "qt"
Project-URL: Home, https://github.com/Zen-Master-SoSo/conn_jack
Provides-Extra: qt
